Workbook

Sheet 3_statement_model
B2: NIKE, Inc. NYSE(NKE)
B3: 3-statement Model
B5: $ in millions | C5: Actuals | H5: Forecast
B6: Assumptions | C6: FY2022 | D6: FY2023 | E6: FY2024 | F6: FY2025 | G6: FY2026 | H6: FY2027 | I6: FY2028 | J6: FY2029 | K6: FY2030 | L6: FY2031
B8: Revenue Growth Rate (% Change) | C8: =C29 -> - | D8: =D29 -> 0.096488975 | E8: =E29 -> 0.0028310912 | F8: =F29 -> -0.098380125 | G8: =G29 -> 0.0019218726 | H8: =H29 -> -0.074264623 | I8: =I29 -> 0.02504138 | J8: =J29 -> 0.046739299 | ... L8: =L29 -> 0.046958726
B9: Cost of Goods Sold (% of Revenue) | C9: =C30/C28 -> 0.54016271 | D9: =D30/D28 -> 0.56475389 | E9: =E30/E28 -> 0.55439819 | F9: =F30/F28 -> 0.57265326 | G9: =G30/G28 -> 0.57086512 | H9: =H30/H28 -> 0.56056664 | I9: =I30/I28 -> 0.56056664 | J9: =J30/J28 -> 0.56056664 | ... L9: =L30/L28 -> 0.56056664
B10: Demand creation expense | C10: =C34/C28 -> 0.082423464 | D10: =D34/D28 -> 0.079270555 | E10: =E34/E28 -> 0.083427437 | F10: =F34/F28 -> 0.10125462 | G10: =G34/G28 -> 0.10246131 | H10: =Notes!C35 -> 0.10185796 | I10: =H10 -> 0.10185796 | J10: =I10 -> 0.10185796 | K10: =J10 -> 0.10185796 | L10: =K10 -> 0.10185796
B11: Operating overhead expense (% of Revenue) | C11: =C35/C28 -> 0.23451081 | D11: =D35/D28 -> 0.24048656 | E11: =E35/E28 -> 0.23930143 | F11: =F35/F28 -> 0.24615086 | G11: =G35/G28 -> 0.24483814 | H11: =Notes!C36 -> 0.2454945 | I11: =H11 -> 0.2454945 | J11: =I11 -> 0.2454945 | K11: =J11 -> 0.2454945 | L11: =K11 -> 0.2454945
B12: Depreciation & Amortization (% of Revenue) | C12: =C108/C28 -> 0.017983301 | D12: =D108/D28 -> 0.016771775 | E12: =E108/E28 -> 0.015497839 | F12: =F108/F28 -> 0.016735408 | G12: =G108/G28 -> 0.016099832 | H12: =Notes!C40 -> 0.016617631 | I12: =H12 -> 0.016617631 | J12: =I12 -> 0.016617631 | K12: =J12 -> 0.016617631 | L12: =K12 -> 0.016617631
B13: Net interest (% of debt) | C13: =C41/(C78+C79+C85) -> 0.02173913 | D13: =D41/(D78+D79+D85) -> -0.00067166685 | E13: =E41/(E78+E79+E85) -> -0.018071613 | F13: =F41/(F78+F79+F85) -> -0.013440523 | G13: =G41/(G78+G79+G85) -> -0.0062956434 | H13: =Notes!C57 -> 0.040621266 | I13: =H13 -> 0.040621266 | J13: =I13 -> 0.040621266 | K13: =J13 -> 0.040621266 | L13: =K13 -> 0.040621266
B14: Tax Rate (%of earning before tax) | C14: =C47 -> 0.090963765 | D14: =D47 -> 0.18238994 | E14: =E47 -> 0.14925373 | F14: =F47 -> 0.17142857 | G14: =G47 -> 0.20307692 | H14: =Notes!C53 -> 0.20307692 | I14: =H14 -> 0.20307692 | J14: =I14 -> 0.20307692 | K14: =J14 -> 0.20307692 | L14: =K14 -> 0.20307692
B15: Accounts Receivable (Days) | C15: =C66/C28*365 -> 36.468743 | D15: =D66/D28*365 -> 29.439737 | E15: =E66/E28*365 -> 31.460126 | F15: =F66/F28*365 -> 37.178626 | G15: =G66/G28*365 -> 46.657507 | H15: =Notes!C45 -> 41.918066 | I15: =H15 -> 41.918066 | J15: =I15 -> 41.918066 | K15: =J15 -> 41.918066 | L15: =K15 -> 41.918066
B16: Inventory (Days) | C16: =(C67/C30)*365 -> 121.80651 | D16: =(D67/D30)*365 -> 106.67969 | E16: =(E67/E30)*365 -> 96.380509 | F16: =(F67/F30)*365 -> 103.07647 | G16: =(G67/G30)*365 -> 103.36637 | H16: =Notes!C46 -> 103.22142 | I16: =H16 -> 103.22142 | J16: =I16 -> 103.22142 | K16: =J16 -> 103.22142 | L16: =K16 -> 103.22142
B17: Accounts Payables (Days) | C17: =C80/C30*365 -> 48.57794 | D17: =D80/D30*365 -> 36.115125 | E17: =E80/E30*365 -> 36.544864 | F17: =F80/F30*365 -> 47.88397 | G17: =G80/G30*365 -> 49.609242 | H17: =Notes!C47 -> 48.746606 | I17: =H17 -> 48.746606 | J17: =I17 -> 48.746606 | K17: =J17 -> 48.746606 | L17: =K17 -> 48.746606
B18: Capital Expenditure (% of revenue) | C18: =C158/C28 -> 0.016227788 | D18: =D158/D28 -> 0.018919499 | E18: =E158/E28 -> 0.015809353 | F18: =F158/F28 -> 0.0092854521 | G18: =G158/G28 -> 0.014742015 | H18: =Notes!C41 -> 0.014996822 | I18: =H18 -> 0.014996822 | J18: =I18 -> 0.014996822 | K18: =J18 -> 0.014996822 | L18: =K18 -> 0.014996822
B19: Debt Issuance(Repayment) | C19: =C127 -> 15 | D19: =D127 -> -504 | E19: =E127 -> 0 | F19: =F127 -> -1000 | G19: =G127 -> 0 | H19: =H127 -> -2000 | I19: =I127 -> 0 | J19: =J127 -> 0 | ... L19: =L127 -> 0
B20: Equity Issued (Repaid) | C20: =C128 -> -2863 | D20: =D128 -> -4829 | E20: =E128 -> -3583 | F20: =F128 -> -2434 | G20: =G128 -> 208 | H20: =H128 -> -750 | I20: =I128 -> -750 | J20: =J128 -> -750 | ... L20: =L128 -> -750
B21: Days in Period | C21: 365 | D21: 365 | E21: 365 | F21: 365 | G21: 365 | H21: 365 | I21: 365 | J21: 365 | K21: 365 | L21: 365
B25: $ in millions | C25: Actuals | H25: Forecast
B26: INCOME STATEMENT (consolidated) | C26: FY2022 | D26: FY2023 | E26: FY2024 | F26: FY2025 | G26: FY2026 | H26: FY2027 | I26: FY2028 | J26: FY2029 | K26: FY2030 | L26: FY2031
B28: Revenues | C28: 46710 | D28: 51217 | E28: 51362 | F28: 46309 | G28: 46398 | H28: =Revenue_Build!H16 -> 42952.27 | I28: =Revenue_Build!I16 -> 44027.854 | J28: =Revenue_Build!J16 -> 46085.685 | K28: =Revenue_Build!K16 -> 48244.808 | L28: =Revenue_Build!L16 -> 50510.323
B29: Revenue Growth | C29: - | D29: =(D28-C28)/C28 -> 0.096488975 | E29: =(E28-D28)/D28 -> 0.0028310912 | F29: =(F28-E28)/E28 -> -0.098380125 | G29: =(G28-F28)/F28 -> 0.0019218726 | H29: =(H28-G28)/G28 -> -0.074264623 | I29: =(I28-H28)/H28 -> 0.02504138 | J29: =(J28-I28)/I28 -> 0.046739299 | K29: =(K28-J28)/J28 -> 0.046850194 | L29: =(L28-K28)/K28 -> 0.046958726
B30: COGS | C30: 25231 | D30: 28925 | E30: 28475 | F30: 26519 | G30: 26487 | H30: =H28-H31 -> 24077.609 | I30: =I28-I31 -> 24680.546 | J30: =J28-J31 -> 25834.097 | K30: =K28-K31 -> 27044.43 | L30: =L28-L31 -> 28314.402
B31: Gross profit | C31: =C28-C30 -> 21479 | D31: =D28-D30 -> 22292 | E31: =E28-E30 -> 22887 | F31: =F28-F30 -> 19790 | G31: =G28-G30 -> 19911 | H31: =H28*H32 -> 18874.661 | I31: =I28*I32 -> 19347.308 | J31: =J28*J32 -> 20251.588 | K31: =K28*K32 -> 21200.378 | L31: =L28*L32 -> 22195.921
B32: Gross Profit Margin % | C32: =C31/C28 -> 0.45983729 | D32: =D31/D28 -> 0.43524611 | E32: =E31/E28 -> 0.44560181 | F32: =F31/F28 -> 0.42734674 | G32: =G31/G28 -> 0.42913488 | H32: =Notes!$C$34 -> 0.43943336 | I32: =H32 -> 0.43943336 | J32: =I32 -> 0.43943336 | K32: =J32 -> 0.43943336 | L32: =K32 -> 0.43943336
B33: Expenses
B34: Demand creation expense | C34: 3850 | D34: 4060 | E34: 4285 | F34: 4689 | G34: 4754 | H34: =H28*H10 -> 4375.0308 | I34: =I28*I10 -> 4484.5876 | J34: =J28*J10 -> 4694.1941 | K34: =K28*K10 -> 4914.118 | L34: =L28*L10 -> 5144.8787
B35: Operating overhead expense | C35: 10954 | D35: 12317 | E35: 12291 | F35: 11399 | G35: 11360 | H35: =H28*H11 -> 10544.546 | I35: =I28*I11 -> 10808.596 | J35: =J28*J11 -> 11313.782 | K35: =K28*K11 -> 11843.835 | L35: =L28*L11 -> 12400.006
B36: Total selling and administrative expense | C36: =C34+C35 -> 14804 | D36: =D34+D35 -> 16377 | E36: =E34+E35 -> 16576 | F36: =F34+F35 -> 16088 | G36: =G34+G35 -> 16114 | H36: =H34+H35 -> 14919.577 | I36: =I34+I35 -> 15293.184 | J36: =J34+J35 -> 16007.976 | ... L36: =L34+L35 -> 17544.885
B37: S&G expense % of Sales | C37: =C36/C28 -> 0.31693428 | D37: =D36/D28 -> 0.31975711 | E37: =E36/E28 -> 0.32272887 | F37: =F36/F28 -> 0.34740547 | G37: =G36/G28 -> 0.34729945 | H37: =H36/H28 -> 0.34735246 | I37: =I36/I28 -> 0.34735246 | J37: =J36/J28 -> 0.34735246 | ... L37: =L36/L28 -> 0.34735246
B39: Operating Income (EBIT) | C39: =C31-C36 -> 6675 | D39: =D31-D36 -> 5915 | E39: =E31-E36 -> 6311 | F39: =F31-F36 -> 3702 | G39: =G31-G36 -> 3797 | H39: =H31-H36 -> 3955.0838 | I39: =I31-I36 -> 4054.1245 | J39: =J31-J36 -> 4243.6115 | ... L39: =L31-L36 -> 4651.0361
B40: EBIT Margin (%) | C40: =C39/C28 -> 0.14290302 | D40: =D39/D28 -> 0.115489 | E40: =E39/E28 -> 0.12287294 | F40: =F39/F28 -> 0.079941264 | G40: =G39/G28 -> 0.081835424 | H40: =H39/H28 -> 0.092080902 | I40: =I39/I28 -> 0.092080902 | J40: =J39/J28 -> 0.092080902 | ... L40: =L39/L28 -> 0.092080902
B41: Interest expense (income), net | C41: 205 | D41: -6 | E41: -161 | F41: -107 | G41: -50 | H41: =H166 -> -38.465902 | I41: =I166 -> -107.48636 | J41: =J166 -> -135.77839 | K41: =K166 -> -167.11696 | L41: =L166 -> -206.77191
B42: Other (income) expense, net | C42: -181 | D42: -280 | E42: -228 | F42: -76 | G42: -53 | H42: =Notes!$C$37 -> 0 | I42: =H42 -> 0 | J42: =I42 -> 0 | K42: =J42 -> 0 | L42: =K42 -> 0
B44: Income before income taxes | C44: =C31-C36-C41-C42 -> 6651 | D44: =D31-D36-D41-D42 -> 6201 | E44: =E31-E36-E41-E42 -> 6700 | F44: =F31-F36-F41-F42 -> 3885 | G44: =G31-G36-G41-G42 -> 3900 | H44: =H31-H36-H41-H42 -> 3993.5497 | I44: =I31-I36-I41-I42 -> 4161.6109 | J44: =J31-J36-J41-J42 -> 4379.3899 | ... L44: =L31-L36-L41-L42 -> 4857.808
B46: Income tax expense | C46: 605 | D46: 1131 | E46: 1000 | F46: 666 | G46: 792 | H46: =H44*H47 -> 810.99778 | I46: =I44*I47 -> 845.12714 | J46: =J44*J47 -> 889.35302 | K46: =K44*K47 -> 936.0917 | L46: =L44*L47 -> 986.50871
B47: Effective Tax Rate | C47: =C46/C44 -> 0.090963765 | D47: =D46/D44 -> 0.18238994 | E47: =E46/E44 -> 0.14925373 | F47: =F46/F44 -> 0.17142857 | G47: =G46/G44 -> 0.20307692 | H47: =H14 -> 0.20307692 | I47: =I14 -> 0.20307692 | J47: =J14 -> 0.20307692 | K47: =K14 -> 0.20307692 | L47: =L14 -> 0.20307692
B49: Net Income | C49: =C44-C46 -> 6046 | D49: =D44-D46 -> 5070 | E49: =E44-E46 -> 5700 | F49: =F44-F46 -> 3219 | G49: =G44-G46 -> 3108 | H49: =H44-H46 -> 3182.5519 | I49: =I44-I46 -> 3316.4838 | J49: =J44-J46 -> 3490.0368 | ... L49: =L44-L46 -> 3871.2993
B50: Net Income Margin | C50: =C49/C28 -> 0.12943695 | D50: =D49/D28 -> 0.09899057 | E50: =E49/E28 -> 0.11097699 | F50: =F49/F28 -> 0.069511326 | G50: =G49/G28 -> 0.066985646 | H50: =H49/H28 -> 0.07409508 | I50: =I49/I28 -> 0.075326945 | J50: =J49/J28 -> 0.075729304 | ... L50: =L49/L28 -> 0.076643725
B52: Earnings per share and shares
B53: Basic EPS ($) | C53: =C49/C55 -> 3.8294908 | D53: =D49/D55 -> 3.2675947 | E53: =E49/E55 -> 3.7559304 | F53: =F49/F55 -> 2.1678227 | G53: =G49/G55 -> 2.1002838 | H53: =H49/H55 -> 2.1615668 | I53: =I49/I55 -> 2.2856427 | J53: =J49/J55 -> 2.4411341 | ... L53: =L49/L55 -> 2.7910887
B54: Diluted EPS ($) | C54: =C49/C56 -> 3.7534145 | D54: =D49/D56 -> 3.2297108 | E54: =E49/E56 -> 3.7262208 | F54: =F49/F56 -> 2.1638881 | G54: =G49/G56 -> 2.098582 | H54: =H49/H56 -> 2.1598065 | I54: =I49/I56 -> 2.283754 | J54: =J49/J56 -> 2.4390868 | ... L54: =L49/L56 -> 2.788676
B55: Weighted average shares – basic | C55: 1578.8 | D55: 1551.6 | E55: 1517.6 | F55: 1484.9 | G55: 1479.8 | H55: =AVERAGE(G58,H58) -> 1472.3357 | I55: =AVERAGE(H58,I58) -> 1451.0071 | J55: =AVERAGE(I58,J58) -> 1429.6785 | K55: =AVERAGE(J58,K58) -> 1408.3499 | L55: =AVERAGE(K58,L58) -> 1387.0212
B56: Weighted average shares – diluted | C56: 1610.8 | D56: 1569.8 | E56: 1529.7 | F56: 1487.6 | G56: 1481 | H56: =H55+Notes!$C$66 -> 1473.5357 | I56: =I55+Notes!$C$66 -> 1452.2071 | J56: =J55+Notes!$C$66 -> 1430.8785 | K56: =K55+Notes!$C$66 -> 1409.5499 | L56: =L55+Notes!$C$66 -> 1388.2212
B57: Dividends declared per share ($) | C57: 1.19 | D57: 1.325 | E57: 1.45 | F57: 1.57 | G57: 1.63 | H57: =G57*(1+Notes!$C$61) -> 1.67075 | I57: =H57*(1+Notes!$C$61) -> 1.7125187 | J57: =I57*(1+Notes!$C$61) -> 1.7553317 | K57: =J57*(1+Notes!$C$61) -> 1.799215 | L57: =K57*(1+Notes!$C$61) -> 1.8441954
B58: Shares outstanding – year end (mm) | C58: 1571 | D58: 1532 | E58: 1503 | F58: 1476 | G58: =Notes!C64 -> 1483 | H58: =G58+Notes!$C$65-Notes!$C$62/Notes!$C$63 -> 1461.6714 | I58: =H58+Notes!$C$65-Notes!$C$62/Notes!$C$63 -> 1440.3428 | J58: =I58+Notes!$C$65-Notes!$C$62/Notes!$C$63 -> 1419.0142 | K58: =J58+Notes!$C$65-Notes!$C$62/Notes!$C$63 -> 1397.6856 | L58: =K58+Notes!$C$65-Notes!$C$62/Notes!$C$63 -> 1376.3569
B60: $ in millions | C60: Actuals | H60: Forecast
B61: BALANCE SHEETS (as of May 31) (consolidated) | C61: FY2022 | D61: FY2023 | E61: FY2024 | F61: FY2025 | G61: FY2026 | H61: FY2027 | I61: FY2028 | J61: FY2029 | K61: FY2030 | L61: FY2031
B63: Assets
B64: Cash and equivalents | C64: 8574 | D64: 7441 | E64: 9860 | F64: 7464 | G64: 7563 | H64: =H137 -> 7257.4481 | I64: =I137 -> 7964.7488 | J64: =J137 -> 8748.2132 | K64: =K137 -> 8216.2894 | L64: =L137 -> 9385.5054
B65: Short-term investments | C65: 4423 | D65: 3234 | E65: 1722 | F65: 1687 | G65: 1464 | H65: =G65 -> 1464 | I65: =H65 -> 1464 | J65: =I65 -> 1464 | K65: =J65 -> 1464 | L65: =K65 -> 1464
B66: Accounts receivable, net | C66: 4667 | D66: 4131 | E66: 4427 | F66: 4717 | G66: 5931 | H66: =H28*H15/365 -> 4932.8113 | I66: =I28*I15/365 -> 5056.3357 | J66: =J28*J15/365 -> 5292.6652 | K66: =K28*K15/365 -> 5540.6276 | L66: =L28*L15/365 -> 5800.8085
B67: Inventories | C67: 8420 | D67: 8454 | E67: 7519 | F67: 7489 | G67: 7501 | H67: =H30*H16/365 -> 6809.1098 | I67: =I30*I16/365 -> 6979.6193 | J67: =J30*J16/365 -> 7305.8418 | K67: =K30*K16/365 -> 7648.1219 | L67: =L30*L16/365 -> 8007.2679
B68: Prepaid expenses and other current assets | C68: 2129 | D68: 1942 | E68: 1854 | F68: 2005 | G68: 2144 | H68: =H28*Notes!$C$48 -> 1922.2216 | I68: =I28*Notes!$C$48 -> 1970.3567 | J68: =J28*Notes!$C$48 -> 2062.4498 | K68: =K28*Notes!$C$48 -> 2159.076 | L68: =L28*Notes!$C$48 -> 2260.4634
B69: Total current assets | C69: =SUM(C64:C68) -> 28213 | D69: =SUM(D64:D68) -> 25202 | E69: =SUM(E64:E68) -> 25382 | F69: =SUM(F64:F68) -> 23362 | G69: =SUM(G64:G68) -> 24603 | H69: =SUM(H64:H68) -> 22385.591 | I69: =SUM(I64:I68) -> 23435.06 | J69: =SUM(J64:J68) -> 24873.17 | ... L69: =SUM(L64:L68) -> 26918.045
B70: Property, plant and equipment, net | C70: 4791 | D70: 5081 | E70: 5000 | F70: 4828 | G70: 4796 | H70: =H160 -> 4726.3826 | I70: =I160 -> 4655.0218 | J70: =J160 -> 4580.3257 | K70: =K160 -> 4502.1301 | L70: =L160 -> 4420.2624
B71: Operating lease right-of-use assets, net | C71: 2926 | D71: 2923 | E71: 2718 | F71: 2712 | G71: 2838 | H71: =G71 -> 2838 | I71: =H71 -> 2838 | J71: =I71 -> 2838 | K71: =J71 -> 2838 | L71: =K71 -> 2838
B72: Identifiable intangible assets, net | C72: 286 | D72: 274 | E72: 259 | F72: 259 | G72: 259 | H72: =G72 -> 259 | I72: =H72 -> 259 | J72: =I72 -> 259 | K72: =J72 -> 259 | L72: =K72 -> 259
B73: Goodwill | C73: 284 | D73: 281 | E73: 240 | F73: 240 | G73: 240 | H73: =G73 -> 240 | I73: =H73 -> 240 | J73: =I73 -> 240 | K73: =J73 -> 240 | L73: =K73 -> 240
B74: Deferred income taxes and other assets | C74: 3821 | D74: 3770 | E74: 4511 | F74: 5178 | G74: 5674 | H74: =G74 -> 5674 | I74: =H74 -> 5674 | J74: =I74 -> 5674 | K74: =J74 -> 5674 | L74: =K74 -> 5674
B75: TOTAL ASSETS | C75: =C69+SUM(C70:C74) -> 40321 | D75: =D69+SUM(D70:D74) -> 37531 | E75: =E69+SUM(E70:E74) -> 38110 | F75: =F69+SUM(F70:F74) -> 36579 | G75: =G69+SUM(G70:G74) -> 38410 | H75: =H69+SUM(H70:H74) -> 36122.973 | I75: =I69+SUM(I70:I74) -> 37101.082 | J75: =J69+SUM(J70:J74) -> 38464.496 | ... L75: =L69+SUM(L70:L74) -> 40349.308
B77: Liabilities
B78: Current portion of long-term debt | C78: 500 | D78: 0 | E78: 1000 | F78: 0 | G78: 2000 | H78: 0 | I78: 0 | J78: 0 | K78: 0 | L78: 0
B79: Notes payable | C79: 10 | D79: 6 | E79: 6 | F79: 0 | G79: 0 | H79: 0 | I79: 0 | J79: 0 | K79: 0 | L79: 0
B80: Accounts payable | C80: 3358 | D80: 2862 | E80: 2851 | F80: 3479 | G80: 3600 | H80: =H30*H17/365 -> 3215.6212 | I80: =I30*I17/365 -> 3296.1448 | J80: =J30*J17/365 -> 3450.2043 | K80: =K30*K17/365 -> 3611.8471 | L80: =L30*L17/365 -> 3781.4548
B81: Current portion of operating lease liabilities | C81: 420 | D81: 425 | E81: 477 | F81: 502 | G81: 478 | H81: =G81 -> 478 | I81: =H81 -> 478 | J81: =I81 -> 478 | K81: =J81 -> 478 | L81: =K81 -> 478
B82: Accrued liabilities | C82: 6220 | D82: 5723 | E82: 5725 | F82: 5916 | G82: 6092 | H82: =H28*Notes!$C$49 -> 5563.3779 | I82: =I28*Notes!$C$49 -> 5702.6926 | J82: =J28*Notes!$C$49 -> 5969.2324 | K82: =K28*Notes!$C$49 -> 6248.8921 | L82: =L28*Notes!$C$49 -> 6542.3321
B83: Income taxes payable | C83: 222 | D83: 240 | E83: 534 | F83: 669 | G83: 377 | H83: =H46*Notes!$C$50 -> 386.04314 | I83: =I46*Notes!$C$50 -> 402.28905 | J83: =J46*Notes!$C$50 -> 423.34102 | K83: =K46*Notes!$C$50 -> 445.5891 | L83: =L46*Notes!$C$50 -> 469.58811
B84: Total current liabilities | C84: =SUM(C78:C83) -> 10730 | D84: =SUM(D78:D83) -> 9256 | E84: =SUM(E78:E83) -> 10593 | F84: =SUM(F78:F83) -> 10566 | G84: =SUM(G78:G83) -> 12547 | H84: =SUM(H78:H83) -> 9643.0423 | I84: =SUM(I78:I83) -> 9879.1264 | J84: =SUM(J78:J83) -> 10320.778 | ... L84: =SUM(L78:L83) -> 11271.375
B85: Long-term debt | C85: 8920 | D85: 8927 | E85: 7903 | F85: 7961 | G85: 5942 | H85: =H165 -> 5942 | I85: =I165 -> 5942 | J85: =J165 -> 5942 | K85: =K165 -> 4442 | L85: =L165 -> 4442
B86: Operating lease liabilities | C86: 2777 | D86: 2786 | E86: 2566 | F86: 2550 | G86: 2613 | H86: =G86 -> 2613 | I86: =H86 -> 2613 | J86: =I86 -> 2613 | K86: =J86 -> 2613 | L86: =K86 -> 2613
B87: Deferred income taxes and other liabilities | C87: 2613 | D87: 2558 | E87: 2618 | F87: 2289 | G87: 2443 | H87: =G87 -> 2443 | I87: =H87 -> 2443 | J87: =I87 -> 2443 | K87: =J87 -> 2443 | L87: =K87 -> 2443
B88: Total liabilities | C88: =C84+SUM(C85:C87) -> 25040 | D88: =D84+SUM(D85:D87) -> 23527 | E88: =E84+SUM(E85:E87) -> 23680 | F88: =F84+SUM(F85:F87) -> 23366 | G88: =G84+SUM(G85:G87) -> 23545 | H88: =H84+SUM(H85:H87) -> 20641.042 | I88: =I84+SUM(I85:I87) -> 20877.126 | J88: =J84+SUM(J85:J87) -> 21318.778 | ... L88: =L84+SUM(L85:L87) -> 20769.375
B90: Shareholders' equity
B91: Common Stock | C91: 3 | D91: 3 | E91: 3 | F91: 3 | G91: 3 | H91: =G91 -> 3 | I91: =H91 -> 3 | J91: =I91 -> 3 | K91: =J91 -> 3 | L91: =K91 -> 3
B92: Capital in excess of stated value | C92: 11484 | D92: 12412 | E92: 13409 | F92: 14195 | G92: 15158 | H92: =G92+H109+Notes!$C$67 -> 16052.284 | I92: =H92+I109+Notes!$C$67 -> 16962.702 | J92: =I92+J109+Notes!$C$67 -> 17903.987 | K92: =J92+K109+Notes!$C$67 -> 18877.659 | L92: =K92+L109+Notes!$C$67 -> 19885.314
B93: Accumulated other comprehensive income | C93: 318 | D93: 231 | E93: 53 | F93: -258 | G93: -141 | H93: =G93 -> -141 | I93: =H93 -> -141 | J93: =I93 -> -141 | K93: =J93 -> -141 | L93: =K93 -> -141
B94: Retained earnings | C94: 3476 | D94: 1358 | E94: 965 | F94: -727 | G94: -155 | H94: =G94+H49+H129-Notes!$C$62 -> -432.35296 | I94: =H94+I49+I129-Notes!$C$62 -> -600.74604 | J94: =I94+J49+J129-Notes!$C$62 -> -620.26916 | K94: =J94+K49+K129-Notes!$C$62 -> -480.74261 | L94: =K94+L49+L129-Notes!$C$62 -> -167.38146
B95: Total shareholders' equity | C95: =SUM(C91:C94) -> 15281 | D95: =SUM(D91:D94) -> 14004 | E95: =SUM(E91:E94) -> 14430 | F95: =SUM(F91:F94) -> 13213 | G95: =SUM(G91:G94) -> 14865 | H95: =SUM(H91:H94) -> 15481.931 | I95: =SUM(I91:I94) -> 16223.956 | J95: =SUM(J91:J94) -> 17145.718 | ... L95: =SUM(L91:L94) -> 19579.933
B97: TOTAL LIABILITIES AND SHAREHOLDERS' EQUITY | C97: =C88+C95 -> 40321 | D97: =D88+D95 -> 37531 | E97: =E88+E95 -> 38110 | F97: =F88+F95 -> 36579 | G97: =G88+G95 -> 38410 | H97: =H88+H95 -> 36122.973 | I97: =I88+I95 -> 37101.082 | J97: =J88+J95 -> 38464.496 | ... L97: =L88+L95 -> 40349.308
B99: Check: Total Assets = Total Liabilities + Shareholder's Equity | C99: =ROUND(C75,2)=ROUND(C97,2) -> TRUE | D99: =ROUND(D75,2)=ROUND(D97,2) -> TRUE | E99: =ROUND(E75,2)=ROUND(E97,2) -> TRUE | F99: =ROUND(F75,2)=ROUND(F97,2) -> TRUE | G99: =ROUND(G75,2)=ROUND(G97,2) -> TRUE | H99: =ROUND(H75,2)=ROUND(H97,2) -> TRUE | I99: =ROUND(I75,2)=ROUND(I97,2) -> TRUE | J99: =ROUND(J75,2)=ROUND(J97,2) -> TRUE | ... L99: =ROUND(L75,2)=ROUND(L97,2) -> TRUE
B102: $ in millions | C102: Actuals | H102: Forecast
B103: CASH FLOWS (consolidated) | C103: FY2022 | D103: FY2023 | E103: FY2024 | F103: FY2025 | G103: FY2026 | H103: FY2027 | I103: FY2028 | J103: FY2029 | K103: FY2030 | L103: FY2031
B105: Operating Activities
B107: Net income | C107: =C49 -> 6046 | D107: =D49 -> 5070 | E107: =E49 -> 5700 | F107: =F49 -> 3219 | G107: =G49 -> 3108 | H107: =H49 -> 3182.5519 | I107: =I49 -> 3316.4838 | J107: =J49 -> 3490.0368 | ... L107: =L49 -> 3871.2993
B108: Total Depreciation & Amortization | C108: 840 | D108: 859 | E108: 796 | F108: 775 | G108: 747 | H108: =H159 -> 713.76497 | I108: =I159 -> 731.63863 | J108: =J159 -> 765.83491 | K108: =K159 -> 801.71442 | L108: =L159 -> 839.36191
B109: Other Non-Cash Items | C109: -38 | D109: 425 | E109: 217 | F109: 491 | G109: 691 | H109: =H28*Notes!$C$42 -> 644.28405 | I109: =I28*Notes!$C$42 -> 660.41781 | J109: =J28*Notes!$C$42 -> 691.28528 | K109: =K28*Notes!$C$42 -> 723.67213 | L109: =L28*Notes!$C$42 -> 757.65485
B110: Total Non Cash Item | C110: =SUM(C108:C109) -> 802 | D110: =SUM(D108:D109) -> 1284 | E110: =SUM(E108:E109) -> 1013 | F110: =SUM(F108:F109) -> 1266 | G110: =SUM(G108:G109) -> 1438 | H110: =SUM(H108:H109) -> 1358.049 | I110: =SUM(I108:I109) -> 1392.0564 | J110: =SUM(J108:J109) -> 1457.1202 | ... L110: =SUM(L108:L109) -> 1597.0168
B111: Change in Accounts Receivable | C111: -504 | D111: 489 | E111: -329 | F111: -257 | G111: -1207 | H111: =G66-H66 -> 998.18874 | I111: =H66-I66 -> -123.5244 | J111: =I66-J66 -> -236.32958 | K111: =J66-K66 -> -247.9624 | L111: =K66-L66 -> -260.18081
B112: Change in Inventories | C112: -1676 | D112: -133 | E112: 908 | F112: 120 | G112: -31 | H112: =G67-H67 -> 691.89024 | I112: =H67-I67 -> -170.5095 | J112: =I67-J67 -> -326.22251 | K112: =J67-K67 -> -342.28011 | L112: =K67-L67 -> -359.14606
B113: Change in Accounts Payable & Other Liabilities | C113: 1365 | D113: -225 | E113: 397 | F113: -426 | G113: -959 | H113: =(H80+H82+H83)-(G80+G82+G83) -> -903.95773 | I113: =(I80+I82+I83)-(H80+H82+H83) -> 236.08417 | J113: =(J80+J82+J83)-(I80+I82+I83) -> 441.65131 | K113: =(K80+K82+K83)-(J80+J82+J83) -> 463.55053 | L113: =(L80+L82+L83)-(K80+K82+K83) -> 487.04675
B114: Change in Other Assets | C114: -845 | D114: -644 | E114: -260 | F114: -224 | G114: 519 | H114: =G68-H68 -> 221.77837 | I114: =H68-I68 -> -48.135082 | J114: =I68-J68 -> -92.093091 | K114: =J68-K68 -> -96.626174 | L114: =K68-L68 -> -101.38746
B115: Total Change in Assets/Liabilities | C115: =SUM(C111:C114) -> -1660 | D115: =SUM(D111:D114) -> -513 | E115: =SUM(E111:E114) -> 716 | F115: =SUM(F111:F114) -> -787 | G115: =SUM(G111:G114) -> -1678 | H115: =SUM(H111:H114) -> 1007.8996 | I115: =SUM(I111:I114) -> -106.08482 | J115: =SUM(J111:J114) -> -212.99387 | ... L115: =SUM(L111:L114) -> -233.66757
B116: Operating Cash Flows | C116: =SUM(C107,C110,C115) -> 5188 | D116: =SUM(D107,D110,D115) -> 5841 | E116: =SUM(E107,E110,E115) -> 7429 | F116: =SUM(F107,F110,F115) -> 3698 | G116: =SUM(G107,G110,G115) -> 2868 | H116: =SUM(H107,H110,H115) -> 5548.5005 | I116: =SUM(I107,I110,I115) -> 4602.4554 | J116: =SUM(J107,J110,J115) -> 4734.1632 | ... L116: =SUM(L107,L110,L115) -> 5234.6485
B118: Investing Activities
B120: Net Change in PP&E (Capex) | C120: -758 | D120: -969 | E120: -812 | F120: -430 | G120: -684 | H120: =-H158 -> -644.14753 | I120: =-I158 -> -660.27787 | J120: =-J158 -> -691.1388 | K120: =-K158 -> -723.51878 | L120: =-L158 -> -757.4943
B121: Net Change in Short-term Investments | C121: -747 | D121: 1481 | E121: 1721 | F121: 147 | G121: 261 | H121: 0 | I121: 0 | J121: 0 | K121: 0 | L121: 0
B122: Investing Activities – Other | C122: -19 | D122: 52 | E122: -15 | F122: 8 | G122: -65 | H122: 0 | I122: 0 | J122: 0 | K122: 0 | L122: 0
B123: Cash Flow from Investing Activities | C123: =SUM(C120:C122) -> -1524 | D123: =SUM(D120:D122) -> 564 | E123: =SUM(E120:E122) -> 894 | F123: =SUM(F120:F122) -> -275 | G123: =SUM(G120:G122) -> -488 | H123: =SUM(H120:H122) -> -644.14753 | I123: =SUM(I120:I122) -> -660.27787 | J123: =SUM(J120:J122) -> -691.1388 | ... L123: =SUM(L120:L122) -> -757.4943
B125: Financing Activities
...

Sheet Revenue_Build
B2: NIKE, Inc. NYSE(NKE)
B3: Revenue_Build
B5: $ in millions | C5: Actuals | H5: Forecast
B6: Revenue | C6: FY2022 | D6: FY2023 | E6: FY2024 | F6: FY2025 | G6: FY2026 | H6: FY2027 | I6: FY2028 | J6: FY2029 | K6: FY2030 | L6: FY2031
B8: North America | C8: 18353 | D8: 21608 | E8: 21396 | F8: 19572 | G8: 20511 | H8: =G8*(1+Notes!C11) -> 20511 | I8: =H8*(1+Notes!C17) -> 21331.44 | J8: =I8*(1+Notes!C23) -> 22398.012 | K8: =J8*(1+Notes!C23) -> 23517.913 | L8: =K8*(1+Notes!C23) -> 24693.808
B9: Europe, Middle East & Africa | C9: 12479 | D9: 13418 | E9: 13607 | F9: 12257 | G9: 12572 | H9: =G9*(1+Notes!C12) -> 11314.8 | I9: =H9*(1+Notes!C18) -> 11654.244 | J9: =I9*(1+Notes!C24) -> 12178.685 | K9: =J9*(1+Notes!C24) -> 12726.726 | L9: =K9*(1+Notes!C24) -> 13299.428
B10: Greater China | C10: 7547 | D10: 7248 | E10: 7545 | F10: 6586 | G10: 5847 | H10: =G10*(1+Notes!C13) -> 4385.25 | I10: =H10*(1+Notes!C19) -> 4165.9875 | J10: =I10*(1+Notes!C25) -> 4270.1372 | K10: =J10*(1+Notes!C25) -> 4376.8906 | L10: =K10*(1+Notes!C25) -> 4486.3129
B11: Asia Pacific & Latin America | C11: 5955 | D11: 6431 | E11: 6729 | F11: 6251 | G11: 6243 | H11: =G11*(1+Notes!C14) -> 5868.42 | I11: =H11*(1+Notes!C20) -> 6044.4726 | J11: =I11*(1+Notes!C26) -> 6407.141 | K11: =J11*(1+Notes!C26) -> 6791.5694 | L11: =K11*(1+Notes!C26) -> 7199.0636
B12: Global Brand Divisions | C12: 102 | D12: 58 | E12: 45 | F12: 48 | G12: 49 | H12: =G12*(1+Notes!$C$29) -> 49 | I12: =H12*(1+Notes!$C$29) -> 49 | J12: =I12*(1+Notes!$C$29) -> 49 | K12: =J12*(1+Notes!$C$29) -> 49 | L12: =K12*(1+Notes!$C$29) -> 49
B13: NIKE Brand revenue | C13: =SUM(C8:C12) -> 44436 | D13: =SUM(D8:D12) -> 48763 | E13: =SUM(E8:E12) -> 49322 | F13: =SUM(F8:F12) -> 44714 | G13: =SUM(G8:G12) -> 45222 | H13: =SUM(H8:H12) -> 42128.47 | I13: =SUM(I8:I12) -> 43245.144 | J13: =SUM(J8:J12) -> 45302.975 | ... L13: =SUM(L8:L12) -> 49727.613
B14: Converse | C14: 2346 | D14: 2427 | E14: 2082 | F14: 1692 | G14: 1174 | H14: =G14*(1+Notes!C$15) -> 821.8 | I14: =H14*(1+Notes!C21) -> 780.71 | J14: =I14*(1+Notes!C27) -> 780.71 | K14: =J14*(1+Notes!C27) -> 780.71 | L14: =K14*(1+Notes!C27) -> 780.71
B15: Corporate | C15: -72 | D15: 27 | E15: -42 | F15: -97 | G15: 2 | H15: =G15*(1+Notes!$C$29) -> 2 | I15: =H15*(1+Notes!$C$29) -> 2 | J15: =I15*(1+Notes!$C$29) -> 2 | K15: =J15*(1+Notes!$C$29) -> 2 | L15: =K15*(1+Notes!$C$29) -> 2
B16: TOTAL NIKE, INC. REVENUE | C16: =C13+C14+C15 -> 46710 | D16: =D13+D14+D15 -> 51217 | E16: =E13+E14+E15 -> 51362 | F16: =F13+F14+F15 -> 46309 | G16: =G13+G14+G15 -> 46398 | H16: =H13+H14+H15 -> 42952.27 | I16: =I13+I14+I15 -> 44027.854 | J16: =J13+J14+J15 -> 46085.685 | ... L16: =L13+L14+L15 -> 50510.323
B17: Revenue growth | C17: - | D17: =D16/C16-1 -> 0.096488975 | E17: =E16/D16-1 -> 0.0028310912 | F17: =F16/E16-1 -> -0.098380125 | G17: =G16/F16-1 -> 0.0019218726 | H17: =H16/G16-1 -> -0.074264623 | I17: =I16/H16-1 -> 0.02504138 | J17: =J16/I16-1 -> 0.046739299 | K17: =K16/J16-1 -> 0.046850194 | L17: =L16/K16-1 -> 0.046958726
B18: Check: 3_statement_model revenue (must be 0) | C18: =C16-'3_statement_model'!C28 -> 0 | D18: =D16-'3_statement_model'!D28 -> 0 | E18: =E16-'3_statement_model'!E28 -> 0 | F18: =F16-'3_statement_model'!F28 -> 0 | G18: =G16-'3_statement_model'!G28 -> 0
B20: YoY growth by segment
B21: North America | C21: - | D21: =(D8/C8)-1 -> 0.1773552 | E21: =(E8/D8)-1 -> -0.009811181 | F21: =(F8/E8)-1 -> -0.085249579 | G21: =(G8/F8)-1 -> 0.047976701 | H21: =H8/G8-1 -> 0 | I21: =I8/H8-1 -> 0.04 | J21: =J8/I8-1 -> 0.05 | K21: =K8/J8-1 -> 0.05 | L21: =L8/K8-1 -> 0.05
B22: EMEA | C22: - | D22: =D9/C9-1 -> 0.075246414 | E22: =E9/D9-1 -> 0.014085557 | F22: =F9/E9-1 -> -0.09921364 | G22: =G9/F9-1 -> 0.0256996 | H22: =H9/G9-1 -> -0.1 | I22: =I9/H9-1 -> 0.03 | J22: =J9/I9-1 -> 0.045 | K22: =K9/J9-1 -> 0.045 | L22: =L9/K9-1 -> 0.045
B23: Greater China | C23: - | D23: =D10/C10-1 -> -0.039618391 | E23: =E10/D10-1 -> 0.040976821 | F23: =F10/E10-1 -> -0.12710404 | G23: =G10/F10-1 -> -0.11220771 | H23: =H10/G10-1 -> -0.25 | I23: =I10/H10-1 -> -0.05 | J23: =J10/I10-1 -> 0.025 | K23: =K10/J10-1 -> 0.025 | L23: =L10/K10-1 -> 0.025
B24: APLA | C24: - | D24: =D11/C11-1 -> 0.07993283 | E24: =E11/D11-1 -> 0.04633805 | F24: =F11/E11-1 -> -0.071035815 | G24: =G11/F11-1 -> -0.0012797952 | H24: =H11/G11-1 -> -0.06 | I24: =I11/H11-1 -> 0.03 | J24: =J11/I11-1 -> 0.06 | K24: =K11/J11-1 -> 0.06 | L24: =L11/K11-1 -> 0.06
B25: Converse | C25: - | D25: =D14/C14-1 -> 0.034526854 | E25: =E14/D14-1 -> -0.1421508 | F25: =F14/E14-1 -> -0.18731988 | G25: =G14/F14-1 -> -0.30614657 | H25: =H14/G14-1 -> -0.3 | I25: =I14/H14-1 -> -0.05 | J25: =J14/I14-1 -> 0 | K25: =K14/J14-1 -> 0 | L25: =L14/K14-1 -> 0
B27: % of Total Revenue
B28: North America | C28: =C8/C$16 -> 0.39291372 | D28: =D8/D$16 -> 0.42189117 | E28: =E8/E$16 -> 0.41657256 | F28: =F8/F$16 -> 0.42263923 | G28: =G8/G$16 -> 0.44206647 | H28: =H8/H$16 -> 0.47753006 | I28: =I8/I$16 -> 0.48449874 | J28: =J8/J$16 -> 0.48600801 | ... L28: =L8/L$16 -> 0.48888636
B29: EMEA | C29: =C9/C$16 -> 0.26715907 | D29: =D9/D$16 -> 0.26198333 | E29: =E9/E$16 -> 0.26492348 | F29: =F9/F$16 -> 0.26467857 | G29: =G9/G$16 -> 0.27095996 | H29: =H9/H$16 -> 0.26342729 | I29: =I9/I$16 -> 0.26470161 | J29: =J9/J$16 -> 0.26426178 | ... L29: =L9/L$16 -> 0.2633012
B30: Greater China | C30: =C10/C$16 -> 0.1615714 | D30: =D10/D$16 -> 0.14151551 | E30: =E10/E$16 -> 0.14689849 | F30: =F10/F$16 -> 0.14221858 | G30: =G10/G$16 -> 0.12601836 | H30: =H10/H$16 -> 0.10209588 | I30: =I10/I$16 -> 0.094621634 | J30: =J10/J$16 -> 0.092656476 | ... L30: =L10/L$16 -> 0.088819722
B31: APLA | C31: =C11/C$16 -> 0.12748876 | D31: =D11/D$16 -> 0.12556378 | E31: =E11/E$16 -> 0.13101125 | F31: =F11/F$16 -> 0.13498456 | G31: =G11/G$16 -> 0.13455321 | H31: =H11/H$16 -> 0.13662654 | I31: =I11/I$16 -> 0.13728747 | J31: =J11/J$16 -> 0.13902671 | ... L31: =L11/L$16 -> 0.14252658
B32: Converse | C32: =C14/C$16 -> 0.050224791 | D32: =D14/D$16 -> 0.04738661 | E32: =E14/E$16 -> 0.040535805 | F32: =F14/F$16 -> 0.036537174 | G32: =G14/G$16 -> 0.025302815 | H32: =H14/H16 -> 0.019132865 | I32: =I14/I16 -> 0.017732184 | J32: =J14/J16 -> 0.016940401 | K32: =K14/K16 -> 0.016182259 | L32: =L14/L16 -> 0.015456444
B34: NIKE Brand revenue by product (10-K revenue note)
B35: Footwear | C35: 29143 | D35: 33135 | E35: 33427 | F35: 29510 | G35: 29525
B36: Apparel | C36: 13567 | D36: 13843 | E36: 13775 | F36: 12965 | G36: 13449
B37: Equipment | C37: 1624 | D37: 1727 | E37: 2075 | F37: 2191 | G37: 2199
B38: Global Brand Divisions | C38: =C12 -> 102 | D38: =D12 -> 58 | E38: =E12 -> 45 | F38: =F12 -> 48 | G38: =G12 -> 49
B39: NIKE Brand revenue (product view) | C39: =SUM(C35:C38) -> 44436 | D39: =SUM(D35:D38) -> 48763 | E39: =SUM(E35:E38) -> 49322 | F39: =SUM(F35:F38) -> 44714 | G39: =SUM(G35:G38) -> 45222
B40: Check: | C40: =C39-C13 -> 0 | D40: =D39-D13 -> 0 | E40: =E39-E13 -> 0 | F40: =F39-F13 -> 0 | G40: =G39-G13 -> 0
B42: Source: Nike Form 10-K, Business Today, NIKE FY2027 Q1 results

Sheet Notes
B2: NIKE, Inc. NYSE(NKE)
B3: 3-statement Model
B5: Active Scenario: 1=Bear, 2- Base, 3- Bull | C5: 2 | D5: =CHOOSE(C5,"Bear","Base","Bull") -> Base
B7: $ in millions
B8: Parameter | C8: Active | D8: Unit | E8: Notes | G8: Bear | H8: Base | I8: Bull
B10: Revenue Growth & Mix
B11: North America growth – FY2027 | C11: =CHOOSE($C$5,G11,H11,I11) -> 0 | D11: %/year | G11: -0.03 | H11: 0 | I11: 0.03
B12: Europe, Middle East & Africa growth – FY2027 | C12: =CHOOSE($C$5,G12,H12,I12) -> -0.1 | D12: %/year | G12: -0.13 | H12: -0.1 | I12: -0.07
B13: Greater China growth – FY2027 | C13: =CHOOSE($C$5,G13,H13,I13) -> -0.25 | D13: %/year | G13: -0.28 | H13: -0.25 | I13: -0.22
B14: Asia Pacific & Latin America growth – FY2027 | C14: =CHOOSE($C$5,G14,H14,I14) -> -0.06 | D14: %/year | G14: -0.09 | H14: -0.06 | I14: -0.03
B15: Converse growth – FY2027 | C15: =CHOOSE($C$5,G15,H15,I15) -> -0.3 | D15: %/year | G15: -0.33 | H15: -0.3 | I15: -0.27
B17: North America growth – FY2028 | C17: =CHOOSE($C$5,G17,H17,I17) -> 0.04 | D17: %/year | G17: 0.02 | H17: 0.04 | I17: 0.06
B18: Europe, Middle East & Africa growth – FY2028 | C18: =CHOOSE($C$5,G18,H18,I18) -> 0.03 | D18: %/year | G18: 0.01 | H18: 0.03 | I18: 0.05
B19: Greater China growth – FY2028 | C19: =CHOOSE($C$5,G19,H19,I19) -> -0.05 | D19: %/year | G19: -0.07 | H19: -0.05 | I19: -0.03
B20: Asia Pacific & Latin America growth – FY2028 | C20: =CHOOSE($C$5,G20,H20,I20) -> 0.03 | D20: %/year | G20: 0.01 | H20: 0.03 | I20: 0.05
B21: Converse growth – FY2028 | C21: =CHOOSE($C$5,G21,H21,I21) -> -0.05 | D21: %/year | G21: -0.07 | H21: -0.05 | I21: -0.03
B23: North America growth – FY2029-31 | C23: =CHOOSE($C$5,G23,H23,I23) -> 0.05 | D23: %/year | G23: 0.03 | H23: 0.05 | I23: 0.07
B24: Europe, Middle East & Africa growth – FY2029-31 | C24: =CHOOSE($C$5,G24,H24,I24) -> 0.045 | D24: %/year | G24: 0.025 | H24: 0.045 | I24: 0.065
... B27: Converse growth – FY2029-31 | C27: =CHOOSE($C$5,G27,H27,I27) -> 0 | D27: %/year | G27: -0.02 | H27: 0 | I27: 0.02
B29: Global Brand Divisions + Corporate revenue | C29: 0 | D29: %/year | G29: - | H29: - | I29: -
B30: Total revenue growth- FY2027 | C30: =Revenue_Build!H17 -> -0.074264623
B32: Margins & Operating Expenses
B34: Gross Margin | C34: =CHOOSE($C$5,G34,H34,I34) -> 0.43943336 | D34: % | E34: 5-yr average (FY22–26) | G34: =H34-0.5% -> 0.43443336 | H34: =AVERAGE('3_statement_model'!C32:G32) -> 0.43943336 | I34: =H34+0.5% -> 0.44443336
B35: Demand creation expense % of revenue | C35: =AVERAGE('3_statement_model'!F10:G10) -> 0.10185796 | D35: % of revenue | E35: FY25-26 average
B36: Operating overhead expense % of revenue | C36: =CHOOSE($C$5,G36,H36,I36) -> 0.2454945 | D36: % of revenue | E36: FY25-26 avg | G36: =H36+0.5% -> 0.2504945 | H36: =AVERAGE('3_statement_model'!G35/'3_statement_model'!G28,'3_statement_model'!F35/'3_statement_model'!F28) -> 0.2454945 | I36: =H36-0.5% -> 0.2404945
B37: Other (income) expense, net | C37: 0
B39: Depreciation, Capex & Stock Compensation
B40: D&A % of revenue | C40: =AVERAGE('3_statement_model'!C12:G12) -> 0.016617631 | D40: % of revenue | E40: 5-yr average
B41: Capex % of revenue | C41: =AVERAGE('3_statement_model'!C18:G18) -> 0.014996822 | D41: % of revenue | E41: 5-yr average
B42: Stock-based compensation % of revenue | C42: 0.015 | D42: % of revenue | E42: 5-yr average
B44: Working Capital
B45: Receivable days (DSO = AR / revenue x 365) | C45: =AVERAGE('3_statement_model'!F66/'3_statement_model'!F28*365,'3_statement_model'!G66/'3_statement_model'!G28*365) -> 41.918066 | D45: days | E45: FY25-26 average
B46: Inventory days (DIO = inventory / COGS x 365) | C46: =CHOOSE($C$5,G46,H46,I46) -> 103.22142 | D46: days | E46: Bear FY22-23 average, Bull FY24 | G46: =AVERAGE('3_statement_model'!C67/'3_statement_model'!C30*365,'3_statement_model'!D67/'3_statement_model'!D30*365) -> 114.2431 | H46: =AVERAGE('3_statement_model'!F67/'3_statement_model'!F30*365,'3_statement_model'!G67/'3_statement_model'!G30*365) -> 103.22142 | I46: ='3_statement_model'!E67/'3_statement_model'!E30*365 -> 96.380509
B47: Payable days (DPO = AP / COGS x 365) | C47: =AVERAGE('3_statement_model'!F80/'3_statement_model'!F30*365,'3_statement_model'!G80/'3_statement_model'!G30*365) -> 48.746606 | D47: days | E47: FY25-26 average
B48: Prepaid & other current assets % of revenue | C48: =AVERAGE('3_statement_model'!F68/'3_statement_model'!F28,'3_statement_model'!G68/'3_statement_model'!G28) -> 0.044752504 | D48: % of revenue | E48: FY25-26 average
B49: Accrued liabilities % of revenue | C49: =AVERAGE('3_statement_model'!F82/'3_statement_model'!F28,'3_statement_model'!G82/'3_statement_model'!G28) -> 0.12952465 | D49: % of revenue | E49: FY25-26 average
B50: Income taxes payable % of tax expense | C50: =MEDIAN('3_statement_model'!C83/'3_statement_model'!C46,'3_statement_model'!D83/'3_statement_model'!D46,'3_statement_model'!E83/'3_statement_model'!E46,'3_statement_model'!F83/'3_statement_model'!F46,'3_statement_model'!G83/'3_statement_model'!G46) -> 0.4760101 | D50: % of tax | E50: 5-yr median
B52: Tax
B53: Effective tax rate | C53: =CHOOSE($C$5,G53,H53,I53) -> 0.20307692 | D53: % | E53: Base FY26, Bear-Management Guidance, Bull 5-yr Avg | G53: 0.25 | H53: ='3_statement_model'!G47 -> 0.20307692 | I53: =AVERAGE('3_statement_model'!C47:G47) -> 0.15942259
B55: Debt & Interest
B56: Cash interest paid – FY2026 | C56: 323 | D56: $mm | E56: FY26 10-K
B57: Cost of debt (on opening debt) | C57: =C56/AVERAGE('3_statement_model'!F78+'3_statement_model'!F79+'3_statement_model'!F85,'3_statement_model'!G78+'3_statement_model'!G79+'3_statement_model'!G85) -> 0.040621266 | D57: % | E57: Interest paid / Avg FY25–26 debt
B58: Interest income rate on cash & ST investments | C58: 0.04 | D58: % | E58: 3M T-bill 4.28%
B60: Dividends, Buybacks & Shares
B61: Dividend per share growth | C61: =CHOOSE($C$5,G61,H61,I61) -> 0.025 | D61: %/yr | E61: Bear freeze, Bull FY26 actual | G61: 0 | H61: 0.025 | I61: ='3_statement_model'!G57/'3_statement_model'!F57-1 -> 0.038216561
B62: Share repurchases | C62: =CHOOSE($C$5,G62,H62,I62) -> 1000 | D62: $mm/yr | E62: Buyback dipped for FY26 | G62: 0 | H62: 1000 | I62: 2000
B63: Average repurchase price | C63: 35.3 | D63: $/share | E63: NKE close price on 14-Oct-26
B64: Shares outstanding at 31-May-2026 | C64: =281+1202 -> 1483 | D64: mm
B65: Shares issued under employee plans | C65: =C64-(290+1186) -> 7 | D65: mm/yr | E65: FY25 & FY26 net change
B66: Dilutive securities (diluted – basic shares) | C66: ='3_statement_model'!G56-'3_statement_model'!G55 -> 1.2 | D66: mm | E66: FY26 actual
B67: Proceeds from option exercises & stock issuance | C67: 250 | D67: $mm/yr | E67: TTM Aug-26 = $227mm
B69: Held flat at FY2026 (non-operating / not forecastable)
B70: Short-term investments, lease ROU assets & lease liabilities, intangibles, goodwill, deferred taxes & other assets/liabilities.
B72: Source: Nike Form 10-K, NIKE FY2027 Q1 results, Business Today
B73: Basis of Prepration: Historical Figures(FY2022-FY2026), Estimates are guided by Q1 results of FY27, Press releases and Management Guidance
B74: Bear/Bull: +/-3% revenue growth (FY27),+/- 2% (FY28–31), +/-0.5% margins
